esmlab_regrid/__init__.py
esmlab_regrid/config.py
esmlab_regrid/core.py
esmlab_regrid/regrid.yaml
tests/__init__.py
tests/test_core.py
esmlab_regrid-2019.5.1.dist-info/LICENSE
esmlab_regrid-2019.5.1.dist-info/METADATA
esmlab_regrid-2019.5.1.dist-info/WHEEL
esmlab_regrid-2019.5.1.dist-info/top_level.txt
esmlab_regrid-2019.5.1.dist-info/RECORD
