Metadata-Version: 2.1
Name: esmlab-regrid
Version: 2019.5.1
Summary: ESMLab regridding utilities
Home-page: https://github.com/NCAR/esmlab-regrid
Maintainer: Anderson Banihirwe
Maintainer-email: abanihi@ucar.edu
License: Apache 2.0
Keywords: esmlab,regridding,xesmf,esmpy,ESMF,xarray,geosience
Platform: UNKNOWN
Requires-Dist: xarray (>=0.11.2)
Requires-Dist: netcdf4
Requires-Dist: cftime
Requires-Dist: esmpy
Requires-Dist: xesmf
Requires-Dist: scipy
Requires-Dist: numpy
Requires-Dist: esmlab
